librds/__init__.py
librds/af.py
librds/charset.py
librds/comfort.py
librds/datatypes.py
librds/decoder.py
librds/generator.py
librds/interface.py
librds/oda.py
librds-2.1.dist-info/licenses/LICENCE
librds-2.1.dist-info/METADATA
librds-2.1.dist-info/WHEEL
librds-2.1.dist-info/top_level.txt
librds-2.1.dist-info/RECORD
