Metadata-Version: 2.4
Name: librds
Version: 2.1
Summary: RDS Group Generator
Home-page: https://github.com/KubaPro010/librds
Author: KubaPro010
Project-URL: Source, https://github.com/KubaPro010/librds
Keywords: radiodatasystem,rds,broadcast_fm
Classifier: Intended Audience :: Education
Classifier: Intended Audience :: Telecommunications Industry
Classifier: Programming Language :: Python :: 3 :: Only
Classifier: Programming Language :: Python :: 3.10
Classifier: Development Status :: 5 - Production/Stable
Classifier: License :: OSI Approved :: GNU General Public License (GPL)
License-File: LICENCE
Dynamic: author
Dynamic: classifier
Dynamic: description
Dynamic: description-content-type
Dynamic: home-page
Dynamic: keywords
Dynamic: license-file
Dynamic: project-url
Dynamic: summary
